fab_ad/constants.py
fab_ad/fab_ad_diff.py
fab_ad/fab_ad_math.py
fab_ad/fab_ad_session.py
fab_ad/fab_ad_tensor.py
fab_ad-1.0.7.dist-info/LICENCE
fab_ad-1.0.7.dist-info/METADATA
fab_ad-1.0.7.dist-info/WHEEL
fab_ad-1.0.7.dist-info/top_level.txt
fab_ad-1.0.7.dist-info/RECORD
