Metadata-Version: 2.1
Name: fab-ad
Version: 1.0.7
Summary: Fab-AD is a Python package for automatic differentiation.
Author: Saket Joshi, Nikhil Nayak, Harsha Taneru, Nishtha Sardana, Kareema Batool,
Classifier: Programming Language :: Python :: 3
Classifier: License :: OSI Approved :: MIT License
Classifier: Operating System :: OS Independent
Requires-Python: >=3.8
License-File: LICENCE
Requires-Dist: poetry-core (>=1.0.0)
Requires-Dist: setuptools
Requires-Dist: wheel
Requires-Dist: numpy
